dp2rathena/__init__.py
dp2rathena/cli.py
dp2rathena/converter.py
dp2rathena/db/item_db.yml
dp2rathena/db/skill_db.yml
dp2rathena/item_mapper.py
dp2rathena/mob_mapper.py
dp2rathena/mob_skill_mapper.py
dp2rathena-0.4.1.dist-info/entry_points.txt
dp2rathena-0.4.1.dist-info/LICENSE
dp2rathena-0.4.1.dist-info/WHEEL
dp2rathena-0.4.1.dist-info/METADATA
dp2rathena-0.4.1.dist-info/RECORD
